{"metadata": {"dbt_schema_version": "https://schemas.getdbt.com/dbt/run-results/v4.json", "dbt_version": "1.4.1", "generated_at": "2023-03-09T16:12:00.399925Z", "invocation_id": "24db90d1-33f0-4eb3-a21a-3b2ebcf87862", "env": {}}, "results": [{"status": "success", "timing": [{"name": "compile", "started_at": "2023-03-09T16:11:51.437007Z", "completed_at": "2023-03-09T16:11:51.445011Z"}, {"name": "execute", "started_at": "2023-03-09T16:11:51.450343Z", "completed_at": "2023-03-09T16:11:54.422360Z"}], "thread_id": "Thread-1 (worker)", "execution_time": 2.987642526626587, "adapter_response": {"_message": "CREATE TABLE (2.0 rows, 0 processed)", "code": "CREATE TABLE", "rows_affected": 2, "bytes_processed": 0, "location": "US", "project_id": "aec-students", "job_id": "75d06f8c-4a54-4743-b730-e63d8b29373f", "slot_ms": 2764}, "message": "CREATE TABLE (2.0 rows, 0 processed)", "failures": null, "unique_id": "model.coffee_shop.my_first_dbt_model"}, {"status": "success", "timing": [{"name": "compile", "started_at": "2023-03-09T16:11:51.506857Z", "completed_at": "2023-03-09T16:11:51.530108Z"}, {"name": "execute", "started_at": "2023-03-09T16:11:51.533444Z", "completed_at": "2023-03-09T16:11:54.571178Z"}], "thread_id": "Thread-6 (worker)", "execution_time": 3.0761756896972656, "adapter_response": {"_message": "CREATE TABLE (7.0 rows, 278.0 Bytes processed)", "code": "CREATE TABLE", "rows_affected": 7, "bytes_processed": 278, "location": "US", "project_id": "aec-students", "job_id": "3830ee48-01ee-4c45-8295-0a47eaf00b10", "slot_ms": 2771}, "message": "CREATE TABLE (7.0 rows, 278.0 Bytes processed)", "failures": null, "unique_id": "model.coffee_shop.stg_coffee_shop__products"}, {"status": "success", "timing": [{"name": "compile", "started_at": "2023-03-09T16:11:51.475584Z", "completed_at": "2023-03-09T16:11:51.484125Z"}, {"name": "execute", "started_at": "2023-03-09T16:11:51.510450Z", "completed_at": "2023-03-09T16:11:54.696076Z"}], "thread_id": "Thread-5 (worker)", "execution_time": 3.226027727127075, "adapter_response": {"_message": "CREATE TABLE (15.0 rows, 600.0 Bytes processed)", "code": "CREATE TABLE", "rows_affected": 15, "bytes_processed": 600, "location": "US", "project_id": "aec-students", "job_id": "5293f86a-2871-4d18-a4e1-4d39b0829972", "slot_ms": 3417}, "message": "CREATE TABLE (15.0 rows, 600.0 Bytes processed)", "failures": null, "unique_id": "model.coffee_shop.stg_coffee_shop__product_prices"}, {"status": "success", "timing": [{"name": "compile", "started_at": "2023-03-09T16:11:54.431901Z", "completed_at": "2023-03-09T16:11:54.435593Z"}, {"name": "execute", "started_at": "2023-03-09T16:11:54.436255Z", "completed_at": "2023-03-09T16:11:55.353510Z"}], "thread_id": "Thread-8 (worker)", "execution_time": 0.9235713481903076, "adapter_response": {"_message": "CREATE VIEW (0 processed)", "code": "CREATE VIEW", "bytes_processed": 0, "location": "US", "project_id": "aec-students", "job_id": "574c781e-c06c-419d-8ec6-e4ca9f53f3ae", "slot_ms": 0}, "message": "CREATE VIEW (0 processed)", "failures": null, "unique_id": "model.coffee_shop.my_second_dbt_model"}, {"status": "success", "timing": [{"name": "compile", "started_at": "2023-03-09T16:11:51.479051Z", "completed_at": "2023-03-09T16:11:51.492006Z"}, {"name": "execute", "started_at": "2023-03-09T16:11:51.503120Z", "completed_at": "2023-03-09T16:11:56.058006Z"}], "thread_id": "Thread-2 (worker)", "execution_time": 4.613356351852417, "adapter_response": {"_message": "CREATE TABLE (174.4k rows, 12.8 MB processed)", "code": "CREATE TABLE", "rows_affected": 174397, "bytes_processed": 13463696, "location": "US", "project_id": "aec-students", "job_id": "770f7f32-56ca-4a8c-933e-68a5dcac2043", "slot_ms": 5526}, "message": "CREATE TABLE (174.4k rows, 12.8 MB processed)", "failures": null, "unique_id": "model.coffee_shop.stg_coffee_shop__customers"}, {"status": "success", "timing": [{"name": "compile", "started_at": "2023-03-09T16:11:51.484501Z", "completed_at": "2023-03-09T16:11:51.494778Z"}, {"name": "execute", "started_at": "2023-03-09T16:11:51.500753Z", "completed_at": "2023-03-09T16:11:56.891020Z"}], "thread_id": "Thread-4 (worker)", "execution_time": 5.4186930656433105, "adapter_response": {"_message": "CREATE TABLE (192.0k rows, 24.7 MB processed)", "code": "CREATE TABLE", "rows_affected": 192007, "bytes_processed": 25905506, "location": "US", "project_id": "aec-students", "job_id": "5234f006-5452-495d-9f3e-cd28b2a08747", "slot_ms": 6701}, "message": "CREATE TABLE (192.0k rows, 24.7 MB processed)", "failures": null, "unique_id": "model.coffee_shop.stg_coffee_shop__orders"}, {"status": "success", "timing": [{"name": "compile", "started_at": "2023-03-09T16:11:51.481445Z", "completed_at": "2023-03-09T16:11:51.493655Z"}, {"name": "execute", "started_at": "2023-03-09T16:11:51.496688Z", "completed_at": "2023-03-09T16:11:57.294561Z"}], "thread_id": "Thread-3 (worker)", "execution_time": 5.834289073944092, "adapter_response": {"_message": "CREATE TABLE (383.8k rows, 30.7 MB processed)", "code": "CREATE TABLE", "rows_affected": 383845, "bytes_processed": 32242980, "location": "US", "project_id": "aec-students", "job_id": "9c91cf50-088a-4a3c-b25c-e4dee64d1e32", "slot_ms": 8162}, "message": "CREATE TABLE (383.8k rows, 30.7 MB processed)", "failures": null, "unique_id": "model.coffee_shop.stg_coffee_shop__order_items"}, {"status": "success", "timing": [{"name": "compile", "started_at": "2023-03-09T16:11:51.488457Z", "completed_at": "2023-03-09T16:11:51.506156Z"}, {"name": "execute", "started_at": "2023-03-09T16:11:51.516299Z", "completed_at": "2023-03-09T16:12:00.391078Z"}], "thread_id": "Thread-7 (worker)", "execution_time": 8.920133113861084, "adapter_response": {"_message": "CREATE TABLE (5.8m rows, 606.0 MB processed)", "code": "CREATE TABLE", "rows_affected": 5797791, "bytes_processed": 635425762, "location": "US", "project_id": "aec-students", "job_id": "e7ae186e-1db7-49cf-8610-09e50e24e533", "slot_ms": 73917}, "message": "CREATE TABLE (5.8m rows, 606.0 MB processed)", "failures": null, "unique_id": "model.coffee_shop.stg_web_tracking__pageviews"}], "elapsed_time": 10.449217319488525, "args": {"write_json": true, "use_colors": true, "printer_width": 80, "version_check": true, "partial_parse": true, "static_parser": true, "profiles_dir": "/home/vscode/.dbt", "send_anonymous_usage_stats": true, "quiet": false, "no_print": false, "cache_selected_only": false, "which": "run", "rpc_method": "run", "indirect_selection": "eager"}}